LICENSE
MANIFEST.in
README.md
pyproject.toml
setup.cfg
setup.py
sockio/__init__.py
sockio/aio.py
sockio/common.py
sockio/py2.py
sockio/sio.py
sockio.egg-info/PKG-INFO
sockio.egg-info/SOURCES.txt
sockio.egg-info/dependency_links.txt
sockio.egg-info/top_level.txt
sockio.egg-info/zip-safe