Metadata-Version: 2.1
Name: sockio
Version: 0.15.0
Summary: Concurrency agnostic socket API
Home-page: https://tiagocoutinho.github.io/sockio/
Author: Jose Tiago Macara Coutinho
Author-email: coutinhotiago@gmail.com
License: GPLv3+
Project-URL: Documentation, https://tiagocoutinho.github.io/sockio/
Project-URL: Source, https://github.com/tiagocoutinho/sockio/
Keywords: socket,asyncio
Platform: UNKNOWN
Classifier: Development Status :: 2 - Pre-Alpha
Classifier: Intended Audience :: Developers
Classifier: Natural Language :: English
Classifier: Programming Language :: Python :: 2.7
Classifier: Programming Language :: Python :: 3
Classifier: Programming Language :: Python :: 3.5
Classifier: Programming Language :: Python :: 3.6
Classifier: Programming Language :: Python :: 3.7
Classifier: Programming Language :: Python :: 3.8
Classifier: Programming Language :: Python :: 3.9
Requires-Python: >=2.7
